{
    "response": [
        {
            "maintainer": "Ishaan",
            "oem": "Redmi",
            "device": "Note 12 5G/Poco X5",
            "filename": "crDroidAndroid-15.0-20250415-stone-v11.4.zip",
            "download": "https://sourceforge.net/projects/crdroid/files/stone/11.x/crDroidAndroid-15.0-20250415-stone-v11.4.zip/download",
            "timestamp": 1744710715,
            "md5": "7f7ee6bf194220dea1412600d89dee50",
            "sha256": "77984ccf5f9db855a2cec85554c99433e9c0d344feb195d12880a54db45333c2",
            "size": 1220294136,
            "version": "11.4",
            "buildtype": "Weekly",
            "forum": "https://xdaforums.com/t/rom-15-0-stone-crdroid-11-official.4704640/",
            "gapps": "https://sourceforge.net/projects/nikgapps/files/Releases/Android-15/",
            "firmware": "",
            "modem": "",
            "bootloader": "",
            "recovery": "https://sourceforge.net/projects/crdroid/files/stone/11.x/recovery/",
            "paypal": "",
            "telegram": "https://t.me/+HI11neGkqB4zZjll",
            "dt": "https://github.com/crdroidandroid/android_device_xiaomi_stone.git",
            "common-dt": "",
            "kernel": "https://github.com/crdroidandroid/android_kernel_xiaomi_stone"
        }
    ]
}